multiple_select_widget/__init__.py
multiple_select_widget/admin.py
multiple_select_widget/apps.py
multiple_select_widget/urls.py
multiple_select_widget/views.py
multiple_select_widget/widget.py
multiple_select_widget/static/css/multiple_select_widget.css
multiple_select_widget/static/js/multiple_select_widget.js
multiple_select_widget/templates/multiple_select_widget/base.html
multiple_select_widget/templates/multiple_select_widget/multiple_select_widget.html
multiple_select_widget/templatetags/__init__.py
multiple_select_widget/templatetags/removehyphens.py
multiple_select_widget/test_utils/__init__.py
multiple_select_widget/test_utils/test_app/__init__.py
multiple_select_widget/test_utils/test_app/admin.py
multiple_select_widget/test_utils/test_app/apps.py
multiple_select_widget/test_utils/test_app/models.py
multiple_select_widget/test_utils/test_app/migrations/__init__.py
multiple_select_widget-0.1.0.dist-info/AUTHORS.rst
multiple_select_widget-0.1.0.dist-info/LICENSE
multiple_select_widget-0.1.0.dist-info/METADATA
multiple_select_widget-0.1.0.dist-info/WHEEL
multiple_select_widget-0.1.0.dist-info/top_level.txt
multiple_select_widget-0.1.0.dist-info/RECORD
