Metadata-Version: 2.1
Name: multiple-select-widget
Version: 0.1.0
Summary: Multiple Select Widget with autocomplete
Home-page: https://github.com/JPolonia/multiple_select_widget
Author: João Polónia
Author-email: jpolonia@evolutio.pt
License: MIT
Keywords: multiple_select_widget
Platform: UNKNOWN
Classifier: Development Status :: 3 - Alpha
Classifier: Framework :: Django :: 2.1
Classifier: Intended Audience :: Developers
Classifier: License :: OSI Approved :: BSD License
Classifier: Natural Language :: English
Classifier: Programming Language :: Python :: 2
Classifier: Programming Language :: Python :: 2.7
Classifier: Programming Language :: Python :: 3
Classifier: Programming Language :: Python :: 3.5
Classifier: Programming Language :: Python :: 3.6
Requires-Dist: Django (==3.2)
